VerilogCode/CompareToThreshold.v
// -------------------------------------------------------------
// 
// File Name: hdlsrc\edgeDetector\CompareToThreshold.v
// Created: 2024-05-06 23:19:59
// 
// Generated by MATLAB 23.2, HDL Coder 23.2, and Simulink 23.2
// 
// -------------------------------------------------------------


// -------------------------------------------------------------
// 
// Module: CompareToThreshold
// Source Path: edgeDetector/EdgeDetection/CompareToThreshold
// Hierarchy Level: 1
// Model version: 1.2
// 
// -------------------------------------------------------------
/*


This requires a total rewrite as it is using floating point values for some reason :)

This modules takes in data, compares it to a constant value (as set per user) and then outputs 1 or zero depending if it exceeds
the threshold or not

*/


module CompareToThreshold
          (In1,
           u);


  input   [7:0] In1;  // uint8
  output   u;  // double


  wire switch_compare_1;
  wire  Zero_out1;  // ufix64
  wire  Constant_out1;  // ufix64
  wire  Switch_out1;  // ufix64
  
  assign switch_compare_1 = In1 > 8'b00001010;



  assign Zero_out1 = 1'b0;


  assign Constant_out1 = 1'b1;

  assign Switch_out1 = (switch_compare_1 == 1'b0 ? Zero_out1 :
              Constant_out1);


  assign u = Switch_out1;

endmodule  // CompareToThreshold

VerilogCode/compareToThreshold_tb.v
`timescale 1ns/1ns
`include "CompareToThreshold.v"

module CompareToThreshold_tb();
// Inputs
  reg[7:0] value;
  
  // Outputs
  wire result;

  // Instantiate the DUT (Design Under Test)
  CompareToThreshold DUT(
    .In1(value),
    .u(result)
  );

  // Generate clock (optional for this example)
  initial begin
    $dumpfile("compare_tb.vcd");
    $dumpvars(0, CompareToThreshold_tb);
    #10; // Wait for a few time units
    value = 0; // Set an example value
    #10; // Wait again
    for (value = 4; value<13; value = value +1)
        begin
          #10;
        end
    #10;
    value <= 0;
    #10;
    // Add more test cases as needed
    $finish;
  end

endmodule

VerilogCode/compare_tb.vcd
$date
	Thu May 16 21:17:25 2024
$end
$version
	Icarus Verilog
$end
$timescale
	1ns
$end
$scope module CompareToThreshold_tb $end
$var wire 1 ! result $end
$var reg 8 " value [7:0] $end
$scope module DUT $end
$var wire 1 # Constant_out1 $end
$var wire 8 $ In1 [7:0] $end
$var wire 1 % Zero_out1 $end
$var wire 1 ! u $end
$var wire 1 & switch_compare_1 $end
$var wire 1 ' Switch_out1 $end
$upscope $end
$upscope $end
$enddefinitions $end
$comment Show the parameter values. $end
$dumpall
$end
#0
$dumpvars
x'
x&
0%
bx $
1#
bx "
x!
$end
#10
0!
0'
0&
b0 "
b0 $
#20
b100 "
b100 $
#30
b101 "
b101 $
#40
b110 "
b110 $
#50
b111 "
b111 $
#60
b1000 "
b1000 $
#70
b1001 "
b1001 $
#80
b1010 "
b1010 $
#90
1!
1'
1&
b1011 "
b1011 $
#100
b1100 "
b1100 $
#110
b1101 "
b1101 $
#120
0!
0'
0&
b0 "
b0 $
