VerilogCode/Smoothing_Filter.v
// -------------------------------------------------------------
// 
// File Name: hdlsrc\edgeDetector\Smoothing_Filter.v
// Created: 2024-05-06 23:19:59
// 
// Generated by MATLAB 23.2, HDL Coder 23.2, and Simulink 23.2
// 
// -------------------------------------------------------------


// -------------------------------------------------------------
// 
// Module: Smoothing_Filter
// Source Path: edgeDetector/EdgeDetection/Smoothing Filter
// Hierarchy Level: 1
// Model version: 1.2
// 
// -------------------------------------------------------------
/*
This function takes a moving average of the data coming in
Need to test this to see if it works

bit shift for division
*/
module Smoothing_Filter
          (clk,
           reset,
           enb,
           In_Arrary,
           SmoothedArray);


  input wire clk;
  input wire reset;
  input wire enb;
  input wire[7:0] In_Arrary;  // current value
  output reg [7:0] SmoothedArray;  // outputvalue

  reg [7:0] In_Arrary1; // 1 delay
  reg [7:0] In_Arrary2; // 2 delay
  reg [7:0] In_Arrary3; // 3 delay
  reg [7:0] In_Arrary4; // current val


  always @(posedge clk or posedge reset)
    begin : reduced_process
      if (reset == 1'b1) begin //reset all the values to 1
        In_Arrary1 <= 8'b00000000;
        In_Arrary2 <= 8'b00000000;
        In_Arrary3 <= 8'b00000000;
        In_Arrary4 <= 8'b00000000;
      end
      else begin
        if (enb) begin
          In_Arrary4 <= In_Arrary3; // current value -3
          In_Arrary3 <= In_Arrary2; //current value -2
          In_Arrary2 <= In_Arrary1; //current value -1
          In_Arrary1 <= In_Arrary; // current value
          
        end
      end
        // average over 4 values
        SmoothedArray <= (In_Arrary4 + In_Arrary3 +In_Arrary2 + In_Arrary1) >> 2 ; 
    end
    
   
    //assign SmoothedArray <= (In_Arrary4 >> 2) + (In_Arrary3)

endmodule  // Smoothing_Filter

VerilogCode/SmoothingFilter_tb.v
/*
Author: Thomas Greenwood
Test bench for the smoothing filter

*/

`include "Smoothing_Filter.v"

module SmoothingFilter_tb();

reg[7:0] inputArray; // to put the data in
wire[7:0] outputVal; // to see the output data
reg reset; // to reset the data
reg enb; // to enable the module
reg clk;  // for the clk of the module


Smoothing_Filter DUT(
            .clk(clk),
           .reset(reset),
           .enb(enb),
           .In_Arrary(inputArray),
           .SmoothedArray(outputVal)
           );
initial begin
    clk <= 0;
    $dumpfile("Smoothingfilter.vcd"); // for gtkwave for debugging
    $dumpvars(0, SmoothingFilter_tb); // for ^
    reset <= 1;// reset all the values
    #2;
    reset <=0;
    enb <= 1;
    inputArray <=4;
    for (inputArray = 4; inputArray<10; inputArray = inputArray +1) // counts up to five
        begin
          #2;
        end 
    #2;
    #2;
    #2; //gives enough time to let all the values pass through
    $finish;
end
always begin
    #1 clk <= ~clk; // toggling the clock
end
endmodule

VerilogCode/Smoothingfilter.vcd
$date
	Fri May 17 11:41:13 2024
$end
$version
	Icarus Verilog
$end
$timescale
	1s
$end
$scope module SmoothingFilter_tb $end
$var wire 8 ! outputVal [7:0] $end
$var reg 1 " clk $end
$var reg 1 # enb $end
$var reg 8 $ inputArray [7:0] $end
$var reg 1 % reset $end
$scope module DUT $end
$var wire 8 & In_Arrary [7:0] $end
$var wire 1 " clk $end
$var wire 1 # enb $end
$var wire 1 % reset $end
$var reg 8 ' In_Arrary1 [7:0] $end
$var reg 8 ( In_Arrary2 [7:0] $end
$var reg 8 ) In_Arrary3 [7:0] $end
$var reg 8 * In_Arrary4 [7:0] $end
$var reg 8 + SmoothedArray [7:0] $end
$scope begin reduced_process $end
$upscope $end
$upscope $end
$upscope $end
$enddefinitions $end
$comment Show the parameter values. $end
$dumpall
$end
#0
$dumpvars
b0xxxxxx +
b0 *
b0 )
b0 (
b0 '
bx &
1%
bx $
x#
0"
b0xxxxxx !
$end
#1
b0 !
b0 +
1"
#2
0"
1#
0%
b0 $
b0 &
#3
1"
#4
0"
b1 $
b1 &
#5
b1 '
1"
#6
0"
b10 $
b10 &
#7
b10 '
b1 (
1"
#8
0"
b11 $
b11 &
#9
b11 '
b10 (
b1 )
1"
#10
0"
b100 $
b100 &
#11
b1 !
b1 +
b100 '
b11 (
b10 )
b1 *
1"
#12
0"
b101 $
b101 &
#13
b10 !
b10 +
b101 '
b100 (
b11 )
b10 *
1"
#14
0"
#15
b11 !
b11 +
b101 (
b100 )
b11 *
1"
#16
0"
#17
b100 !
b100 +
b101 )
b100 *
1"
